dagster_azure/__init__.py
dagster_azure/py.typed
dagster_azure/version.py
dagster_azure/adls2/__init__.py
dagster_azure/adls2/fake_adls2_resource.py
dagster_azure/adls2/file_manager.py
dagster_azure/adls2/io_manager.py
dagster_azure/adls2/resources.py
dagster_azure/adls2/utils.py
dagster_azure/blob/__init__.py
dagster_azure/blob/compute_log_manager.py
dagster_azure/blob/fake_blob_client.py
dagster_azure/blob/utils.py
dagster_azure-1.0.5.dist-info/LICENSE
dagster_azure-1.0.5.dist-info/METADATA
dagster_azure-1.0.5.dist-info/WHEEL
dagster_azure-1.0.5.dist-info/entry_points.txt
dagster_azure-1.0.5.dist-info/top_level.txt
dagster_azure-1.0.5.dist-info/RECORD
