Metadata-Version: 2.1
Name: dagster-azure
Version: 1.0.5
Summary: Package for Azure-specific Dagster framework op and resource components.
Home-page: https://github.com/dagster-io/dagster/tree/master/python_modules/libraries/dagster-azure
Author: Elementl
Author-email: hello@elementl.com
License: Apache-2.0
Platform: UNKNOWN
Classifier: Programming Language :: Python :: 3.7
Classifier: Programming Language :: Python :: 3.8
Classifier: Programming Language :: Python :: 3.9
Classifier: Programming Language :: Python :: 3.10
Classifier: License :: OSI Approved :: Apache Software License
Classifier: Operating System :: OS Independent
License-File: LICENSE
Requires-Dist: azure-core (<2.0.0,>=1.7.0)
Requires-Dist: azure-storage-blob (<13.0.0,>=12.5.0)
Requires-Dist: azure-storage-file-datalake (<13.0.0,>=12.5)
Requires-Dist: dagster (==1.0.5)
